consolemenu_py/__init__.py
consolemenu_py/menu.py
consolemenu_py/menuitem.py
consolemenu.py-0.2.2.dist-info/LICENSE
consolemenu.py-0.2.2.dist-info/WHEEL
consolemenu.py-0.2.2.dist-info/METADATA
consolemenu.py-0.2.2.dist-info/RECORD
