Metadata-Version: 2.1
Name: consolemenu.py
Version: 0.2.2
Summary: A simple Python console (terminal) menu that work's on any OS
License: MIT
Author: Pirulax
Author-email: patrikjankovics7@gmail.com
Requires-Python: >=3.10,<4.0
Classifier: License :: OSI Approved :: MIT License
Classifier: Programming Language :: Python :: 3
Classifier: Programming Language :: Python :: 3.10
Requires-Dist: aioconsole (>=0.7.0,<0.8.0)
Project-URL: Homepage, https://github.com/Pirulax/consolemenu.py
